simple_multi_mst/__init__.py
simple_multi_mst/py.typed
simple_multi_mst/visual.py
simple_multi_mst-0.1.1.dist-info/METADATA
simple_multi_mst-0.1.1.dist-info/WHEEL
simple_multi_mst-0.1.1.dist-info/RECORD
