Metadata-Version: 2.4
Name: simple-multi-mst
Version: 0.1.1
Summary: Package to build TDA networks based on multiple MSTs
Author-email: Jan Aerts <jan.aerts@kuleuven.be>
Requires-Python: >=3.13
Requires-Dist: numpy>=2.2.5
Requires-Dist: pandas>=2.2.3
Requires-Dist: returns>=0.25.0
Requires-Dist: scipy>=1.15.3
